agora_realtime_ai_api/__init__.py
agora_realtime_ai_api/logger.py
agora_realtime_ai_api/rtc.py
agora_realtime_ai_api/token_builder/AccessToken2.py
agora_realtime_ai_api/token_builder/Packer.py
agora_realtime_ai_api/token_builder/RtcTokenBuilder2.py
agora_realtime_ai_api/token_builder/__init__.py
agora_realtime_ai_api/token_builder/realtimekit_token_builder.py
spatialwalk_agora_realtime_ai_api-1.1.1.dist-info/LICENSE
spatialwalk_agora_realtime_ai_api-1.1.1.dist-info/METADATA
spatialwalk_agora_realtime_ai_api-1.1.1.dist-info/WHEEL
spatialwalk_agora_realtime_ai_api-1.1.1.dist-info/top_level.txt
spatialwalk_agora_realtime_ai_api-1.1.1.dist-info/RECORD
