Metadata-Version: 2.1
Name: spatialwalk-agora-realtime-ai-api
Version: 1.1.1
Summary: spatialwalk fork of Agora's low latency, high performance Realtime API to work with Voice Conversational AI
Home-page: https://github.com/AgoraIO/agora-realtime-ai-api
Author: spatialwalk
Author-email: liyuhang@spatialwalk.net
Classifier: Programming Language :: Python :: 3
Classifier: License :: OSI Approved :: MIT License
Classifier: Operating System :: OS Independent
Requires-Python: >=3.11
License-File: LICENSE
Requires-Dist: pyee ==12.0.0
Requires-Dist: agora-python-server-sdk ==2.2.1
